Metadata-Version: 1.0
Name: distributions-gungz
Version: 0.1
Summary: Gaussian distributions
Home-page: UNKNOWN
Author: Gungz
Author-email: UNKNOWN
License: UNKNOWN
Platform: UNKNOWN
